metal_python_Metal_io/__init__.py
metal_python_Metal_io/metal.py
metal_python_metal_io-0.0.3.dist-info/METADATA
metal_python_metal_io-0.0.3.dist-info/WHEEL
metal_python_metal_io-0.0.3.dist-info/licenses/LICENSE
metal_python_metal_io-0.0.3.dist-info/RECORD
