Metadata-Version: 2.1
Name: metal_python_Metal_io
Version: 0.0.3
Summary: A small example package
Project-URL: Github, https://github.com/getmetal/metal-python
Author-email: Metal Technologies Inc <james@getmetal.io>
License-File: LICENSE
Classifier: License :: OSI Approved :: Apache Software License
Classifier: Programming Language :: Python :: 3
Requires-Python: >=3.7
Requires-Dist: dataclasses
Requires-Dist: pydantic
Requires-Dist: python-dateutil
Requires-Dist: requests
Requires-Dist: typing-extensions
